LICENSE
MANIFEST.in
README.md
pyproject.toml
setup.py
ktransformers/__init__.py
ktransformers/local_chat.py
ktransformers/__pycache__/__init__.cpython-311.pyc
ktransformers/__pycache__/__init__.cpython-312.pyc
ktransformers/__pycache__/local_chat.cpython-311.pyc
ktransformers/__pycache__/local_chat.cpython-312.pyc
ktransformers/configs/config.yaml
ktransformers/configs/log_config.ini
ktransformers/ktransformers_ext/CMakeLists.txt
ktransformers/ktransformers_ext/ext_bindings.cpp
ktransformers/ktransformers_ext/bench/bench_attention.py
ktransformers/ktransformers_ext/bench/bench_attention_torch.py
ktransformers/ktransformers_ext/bench/bench_linear.py
ktransformers/ktransformers_ext/bench/bench_linear_torch.py
ktransformers/ktransformers_ext/bench/bench_mlp.py
ktransformers/ktransformers_ext/bench/bench_mlp_torch.py
ktransformers/ktransformers_ext/bench/bench_moe.py
ktransformers/ktransformers_ext/bench/bench_moe_torch.py
ktransformers/ktransformers_ext/cmake/FindSIMD.cmake
ktransformers/ktransformers_ext/cpu_backend/backend.cpp
ktransformers/ktransformers_ext/cpu_backend/backend.h
ktransformers/ktransformers_ext/cpu_backend/cpuinfer.h
ktransformers/ktransformers_ext/cpu_backend/task_queue.cpp
ktransformers/ktransformers_ext/cpu_backend/task_queue.h
ktransformers/ktransformers_ext/cuda/binding.cpp
ktransformers/ktransformers_ext/cuda/setup.py
ktransformers/ktransformers_ext/cuda/custom_gguf/binding.cpp
ktransformers/ktransformers_ext/cuda/custom_gguf/dequant.cu
ktransformers/ktransformers_ext/cuda/custom_gguf/ops.h
ktransformers/ktransformers_ext/cuda/gptq_marlin/gptq_marlin.cu
ktransformers/ktransformers_ext/cuda/gptq_marlin/gptq_marlin.cuh
ktransformers/ktransformers_ext/cuda/gptq_marlin/gptq_marlin_dtypes.cuh
ktransformers/ktransformers_ext/cuda/gptq_marlin/ops.h
ktransformers/ktransformers_ext/examples/test_attention.py
ktransformers/ktransformers_ext/examples/test_linear.py
ktransformers/ktransformers_ext/examples/test_mlp.py
