Metadata-Version: 2.1
Name: ktransformers
Version: 0.2.1.post1
Summary: KTransformers, pronounced as Quick Transformers, is designed to enhance your Transformers experience with advanced kernel optimizations and placement/parallelism strategies.
Author-email: "KVCache.AI" <zhang.mingxing@outlook.com>
Maintainer-email: james0zan <zhang.mingxing@outlook.com>, awake <awake@approaching.ai>, unicorn chan <nl@approaching.ai>
License:                                  Apache License
Project-URL: Homepage, https://kvcache.ai
Project-URL: Repository, https://github.com/kvcache-ai/ktransformers.git
Project-URL: Issues, https://github.com/kvcache-ai/ktransformers/issues
Keywords: ktransformers,llm
Classifier: Development Status :: 4 - Beta
Classifier: Programming Language :: Python :: 3.10
Classifier: Programming Language :: Python :: 3.11
Classifier: Programming Language :: Python :: 3.12
Requires-Python: >=3.10
License-File: LICENSE
Requires-Dist: torch>=2.3.0
Requires-Dist: transformers==4.43.2
Requires-Dist: fastapi>=0.111.0
Requires-Dist: uvicorn>=0.30.1
Requires-Dist: langchain>=0.2.0
Requires-Dist: blessed>=1.20.0
Requires-Dist: accelerate>=0.31.0
Requires-Dist: sentencepiece>=0.1.97
Requires-Dist: setuptools
Requires-Dist: ninja
Requires-Dist: wheel
Requires-Dist: colorlog
Requires-Dist: build
Requires-Dist: fire
Requires-Dist: protobuf
